<?xml version="1.0" encoding="UTF-8" standalone="yes"?>
<portlet-definition version="4.0" xsi:schemaLocation="https://source.jasig.org/schemas/uportal/io/portlet-definition https://source.jasig.org/schemas/uportal/io/portlet-definition/portlet-definition-4.0.xsd" xmlns:ns2="https://source.jasig.org/schemas/uportal" xmlns="https://source.jasig.org/schemas/uportal/io/portlet-definition" xmlns:ns4="https://source.jasig.org/schemas/uportal/io/permission-owner" xmlns:ns3="https://source.jasig.org/schemas/uportal/io/event-aggregation" xmlns:ns5="https://source.jasig.org/schemas/uportal/io/user" xmlns:ns6="https://source.jasig.org/schemas/uportal/io/stylesheet-descriptor" xmlns:ns7="https://source.jasig.org/schemas/uportal/io/portlet-type" xmlns:xsi="http://www.w3.org/2001/XMLSchema-instance" xmlns:ns8="https://source.jasig.org/schemas/uportal/io/subscribed-fragment">
    <title>Who's Online</title>
    <name>Who's Online</name>
    <fname>whos-online</fname>
    <desc>Mockup of a Who's Online portlet.</desc>
    <type>CMS</type>
    <timeout>10000</timeout>
    <portlet-descriptor>
        <ns2:webAppName>/SimpleContentPortlet</ns2:webAppName>
        <ns2:portletName>cms</ns2:portletName>
    </portlet-descriptor>
    <category>Information</category>
    <group>Portal Developers</group>
    <parameter>
        <name>disableDynamicTitle</name>
        <value>true</value>
    </parameter>
    <parameter>
        <name>iconUrl</name>
        <value>/ResourceServingWebapp/rs/tango/0.8.90/32x32/mimetypes/text-html.png</value>
    </parameter>
    <portlet-preference>
        <name>content</name>
        <readOnly>false</readOnly>
        <value>

            &lt;img src="/uPortal/media/org/jasig/portal/channels/webproxy/whosonline.png"
            alt="uP3 Mock My Courses" border="0" /&gt;

            &lt;p&gt;Mock of Who's Online. This is a sample screen for
            demonstration purposes only.&lt;/p&gt;


        </value>
    </portlet-preference>
</portlet-definition>
